supersecret/__init__.py
supersecret/dto.py
supersecret/exceptions.py
supersecret/fields.py
supersecret/manager.py
supersecret/parser.py
supersecret/util.py
tests/__init__.py
tests/test_aws_connection.py
tests/test_fields.py
tests/test_manager.py
tests/test_other.py
supersecret-1.1.0.dist-info/LICENSE
supersecret-1.1.0.dist-info/METADATA
supersecret-1.1.0.dist-info/WHEEL
supersecret-1.1.0.dist-info/top_level.txt
supersecret-1.1.0.dist-info/RECORD
