Metadata-Version: 2.1
Name: supersecret
Version: 1.1.0
Summary: SuperSecret is a Python library for managing secrets in AWS Secrets Manager.
Home-page: https://github.com/gdoermann/supersecret
Author: Greg Doermann
Author-email: greg@doermann.me
License: MIT
Project-URL: Source, https://github.com/gdoermann/supersecret
Project-URL: Tracker, https://github.com/gdoermann/supersecret/issues
Classifier: Development Status :: 4 - Beta
Classifier: Intended Audience :: Developers
Classifier: License :: OSI Approved :: MIT License
Classifier: Operating System :: OS Independent
Classifier: Programming Language :: Python :: 3.10
Classifier: Programming Language :: Python :: 3.11
Classifier: Topic :: Software Development :: Libraries :: Python Modules
Requires-Python: >=3.8
License-File: LICENSE
Requires-Dist: botocore ~=1.29
Requires-Dist: boto3 ~=1.26
Requires-Dist: marshmallow ~=3.19.0
Requires-Dist: tox ~=4.4.6
Requires-Dist: wheel
Requires-Dist: flake8 ~=6.0.0
Provides-Extra: extras
Requires-Dist: flake8 ; extra == 'extras'
Requires-Dist: twine ; extra == 'extras'
Requires-Dist: pytest ; extra == 'extras'
Requires-Dist: pip-tools ; extra == 'extras'
Requires-Dist: bumpver ; extra == 'extras'
Requires-Dist: coverage ; extra == 'extras'
